[
  {
    "__type__": "cc.Prefab",
    "_name": "Shuriken",
    "_objFlags": 0,
    "_native": "",
    "data": {
      "__id__": 1
    },
    "optimizationPolicy": 0,
    "asyncLoadAssets": false,
    "readonly": false
  },
  {
    "__type__": "cc.Node",
    "_name": "Shuriken",
    "_objFlags": 0,
    "_parent": null,
    "_children": [],
    "_active": true,
    "_components": [
      {
        "__id__": 2
      },
      {
        "__id__": 3
      },
      {
        "__id__": 4
      }
    ],
    "_prefab": {
      "__id__": 5
    },
    "_opacity": 255,
    "_color": {
      "__type__": "cc.Color",
      "r": 255,
      "g": 255,
      "b": 255,
      "a": 255
    },
    "_contentSize": {
      "__type__": "cc.Size",
      "width": 60,
      "height": 60
    },
    "_anchorPoint": {
      "__type__": "cc.Vec2",
      "x": 0.5,
      "y": 0.5
    },
    "_trs": {
      "__type__": "TypedArray",
      "ctor": "Float64Array",
      "array": [
        0,
        132.722,
        0,
        0,
        0,
        0,
        1,
        1,
        1,
        1
      ]
    },
    "_eulerAngles": {
      "__type__": "cc.Vec3",
      "x": 0,
      "y": 0,
      "z": 0
    },
    "_skewX": 0,
    "_skewY": 0,
    "_is3DNode": false,
    "_groupIndex": 4,
    "groupIndex": 4,
    "_id": ""
  },
  {
    "__type__": "cc.Sprite",
    "_name": "",
    "_objFlags": 0,
    "node": {
      "__id__": 1
    },
    "_enabled": true,
    "_materials": [
      {
        "__uuid__": "eca5d2f2-8ef6-41c2-bbe6-f9c79d09c432"
      }
    ],
    "_srcBlendFactor": 770,
    "_dstBlendFactor": 771,
    "_spriteFrame": {
      "__uuid__": "9383b6bc-0d7b-4d7f-a703-11dad79a3d19"
    },
    "_type": 0,
    "_sizeMode": 0,
    "_fillType": 0,
    "_fillCenter": {
      "__type__": "cc.Vec2",
      "x": 0,
      "y": 0
    },
    "_fillStart": 0,
    "_fillRange": 0,
    "_isTrimmedMode": true,
    "_atlas": null,
    "_id": ""
  },
  {
    "__type__": "c7a1dmGKkBD14Hb0ld0GDsF",
    "_name": "",
    "_objFlags": 0,
    "node": {
      "__id__": 1
    },
    "_enabled": true,
    "damage": 20,
    "weaponScale": 1,
    "travelSpeed": 800,
    "hitLimit": 10,
    "isShootingAtTarget": false,
    "duration": 2,
    "startRadius": 150,
    "maxRadius": 150,
    "angleDelta": 0,
    "_id": ""
  },
  {
    "__type__": "cc.PolygonCollider",
    "_name": "",
    "_objFlags": 0,
    "node": {
      "__id__": 1
    },
    "_enabled": true,
    "tag": 2,
    "_offset": {
      "__type__": "cc.Vec2",
      "x": 0,
      "y": 0
    },
    "points": [
      {
        "__type__": "cc.Vec2",
        "x": -2.311827956989248,
        "y": 25
      },
      {
        "__type__": "cc.Vec2",
        "x": -2.311827956989248,
        "y": 23.458781362007166
      },
      {
        "__type__": "cc.Vec2",
        "x": -3.817204301075268,
        "y": 23.458781362007166
      },
      {
        "__type__": "cc.Vec2",
        "x": -3.817204301075268,
        "y": 9.838709677419352
      },
      {
        "__type__": "cc.Vec2",
        "x": -5.286738351254481,
        "y": 9.838709677419352
      },
      {
        "__type__": "cc.Vec2",
        "x": -5.286738351254481,
        "y": 11.344086021505376
      },
      {
        "__type__": "cc.Vec2",
        "x": -8.369175627240143,
        "y": 11.344086021505376
      },
      {
        "__type__": "cc.Vec2",
        "x": -8.369175627240143,
        "y": 9.838709677419352
      },
      {
        "__type__": "cc.Vec2",
        "x": -9.874551971326166,
        "y": 9.838709677419352
      },
      {
        "__type__": "cc.Vec2",
        "x": -9.874551971326166,
        "y": 8.333333333333329
      },
      {
        "__type__": "cc.Vec2",
        "x": -12.92114695340502,
        "y": 8.333333333333329
      },
      {
        "__type__": "cc.Vec2",
        "x": -12.92114695340502,
        "y": 6.827956989247312
      },
      {
        "__type__": "cc.Vec2",
        "x": -14.42652329749104,
        "y": 6.827956989247312
      },
      {
        "__type__": "cc.Vec2",
        "x": -14.42652329749104,
        "y": 5.286738351254478
      },
      {
        "__type__": "cc.Vec2",
        "x": -17.437275985663085,
        "y": 5.286738351254478
      },
      {
        "__type__": "cc.Vec2",
        "x": -17.437275985663085,
        "y": 3.7813620071684575
      },
      {
        "__type__": "cc.Vec2",
        "x": -18.942652329749105,
        "y": 3.7813620071684575
      },
      {
        "__type__": "cc.Vec2",
        "x": -18.942652329749105,
        "y": 2.2759856630824373
      },
      {
        "__type__": "cc.Vec2",
        "x": -21.989247311827956,
        "y": 2.2759856630824373
      },
      {
        "__type__": "cc.Vec2",
        "x": -21.989247311827956,
        "y": 0.7706093189964136
      },
      {
        "__type__": "cc.Vec2",
        "x": -23.49462365591398,
        "y": 0.7706093189964136
      },
      {
        "__type__": "cc.Vec2",
        "x": -23.49462365591398,
        "y": -0.7706093189964172
      },
      {
        "__type__": "cc.Vec2",
        "x": -25,
        "y": -0.7706093189964172
      },
      {
        "__type__": "cc.Vec2",
        "x": -25,
        "y": -2.311827956989248
      },
      {
        "__type__": "cc.Vec2",
        "x": -23.49462365591398,
        "y": -2.311827956989248
      },
      {
        "__type__": "cc.Vec2",
        "x": -23.49462365591398,
        "y": -3.817204301075268
      },
      {
        "__type__": "cc.Vec2",
        "x": -9.874551971326166,
        "y": -3.817204301075268
      },
      {
        "__type__": "cc.Vec2",
        "x": -9.874551971326166,
        "y": -5.286738351254481
      },
      {
        "__type__": "cc.Vec2",
        "x": -11.379928315412187,
        "y": -5.286738351254481
      },
      {
        "__type__": "cc.Vec2",
        "x": -11.379928315412187,
        "y": -8.369175627240143
      },
      {
        "__type__": "cc.Vec2",
        "x": -9.874551971326166,
        "y": -8.369175627240143
      },
      {
        "__type__": "cc.Vec2",
        "x": -9.874551971326166,
        "y": -9.874551971326166
      },
      {
        "__type__": "cc.Vec2",
        "x": -8.369175627240143,
        "y": -9.874551971326166
      },
      {
        "__type__": "cc.Vec2",
        "x": -8.369175627240143,
        "y": -12.885304659498209
      },
      {
        "__type__": "cc.Vec2",
        "x": -6.863799283154123,
        "y": -12.885304659498209
      },
      {
        "__type__": "cc.Vec2",
        "x": -6.863799283154123,
        "y": -14.42652329749104
      },
      {
        "__type__": "cc.Vec2",
        "x": -5.322580645161292,
        "y": -14.42652329749104
      },
      {
        "__type__": "cc.Vec2",
        "x": -5.322580645161292,
        "y": -17.437275985663085
      },
      {
        "__type__": "cc.Vec2",
        "x": -3.817204301075268,
        "y": -17.437275985663085
      },
      {
        "__type__": "cc.Vec2",
        "x": -3.817204301075268,
        "y": -18.942652329749105
      },
      {
        "__type__": "cc.Vec2",
        "x": -2.311827956989248,
        "y": -18.942652329749105
      },
      {
        "__type__": "cc.Vec2",
        "x": -2.311827956989248,
        "y": -21.989247311827956
      },
      {
        "__type__": "cc.Vec2",
        "x": -0.8064516129032278,
        "y": -21.989247311827956
      },
      {
        "__type__": "cc.Vec2",
        "x": -0.8064516129032278,
        "y": -23.49462365591398
      },
      {
        "__type__": "cc.Vec2",
        "x": 0.734767025089603,
        "y": -23.49462365591398
      },
      {
        "__type__": "cc.Vec2",
        "x": 0.734767025089603,
        "y": -25
      },
      {
        "__type__": "cc.Vec2",
        "x": 2.2759856630824373,
        "y": -25
      },
      {
        "__type__": "cc.Vec2",
        "x": 2.2759856630824373,
        "y": -23.49462365591398
      },
      {
        "__type__": "cc.Vec2",
        "x": 3.7813620071684575,
        "y": -23.49462365591398
      },
      {
        "__type__": "cc.Vec2",
        "x": 3.7813620071684575,
        "y": -9.874551971326166
      },
      {
        "__type__": "cc.Vec2",
        "x": 5.250896057347667,
        "y": -9.874551971326166
      },
      {
        "__type__": "cc.Vec2",
        "x": 5.250896057347667,
        "y": -11.379928315412187
      },
      {
        "__type__": "cc.Vec2",
        "x": 8.333333333333329,
        "y": -11.379928315412187
      },
      {
        "__type__": "cc.Vec2",
        "x": 8.333333333333329,
        "y": -9.874551971326166
      },
      {
        "__type__": "cc.Vec2",
        "x": 9.838709677419352,
        "y": -9.874551971326166
      },
      {
        "__type__": "cc.Vec2",
        "x": 9.838709677419352,
        "y": -8.369175627240143
      },
      {
        "__type__": "cc.Vec2",
        "x": 12.885304659498203,
        "y": -8.369175627240143
      },
      {
        "__type__": "cc.Vec2",
        "x": 12.885304659498203,
        "y": -6.863799283154123
      },
      {
        "__type__": "cc.Vec2",
        "x": 14.390681003584227,
        "y": -6.863799283154123
      },
      {
        "__type__": "cc.Vec2",
        "x": 14.390681003584227,
        "y": -5.322580645161292
      },
      {
        "__type__": "cc.Vec2",
        "x": 17.401433691756267,
        "y": -5.322580645161292
      },
      {
        "__type__": "cc.Vec2",
        "x": 17.401433691756267,
        "y": -3.817204301075268
      },
      {
        "__type__": "cc.Vec2",
        "x": 18.9426523297491,
        "y": -3.817204301075268
      },
      {
        "__type__": "cc.Vec2",
        "x": 18.9426523297491,
        "y": -2.311827956989248
      },
      {
        "__type__": "cc.Vec2",
        "x": 21.953405017921142,
        "y": -2.311827956989248
      },
      {
        "__type__": "cc.Vec2",
        "x": 21.953405017921142,
        "y": -0.8064516129032278
      },
      {
        "__type__": "cc.Vec2",
        "x": 23.458781362007166,
        "y": -0.8064516129032278
      },
      {
        "__type__": "cc.Vec2",
        "x": 23.458781362007166,
        "y": 0.734767025089603
      },
      {
        "__type__": "cc.Vec2",
        "x": 25,
        "y": 0.734767025089603
      },
      {
        "__type__": "cc.Vec2",
        "x": 25,
        "y": 2.2759856630824373
      },
      {
        "__type__": "cc.Vec2",
        "x": 23.458781362007166,
        "y": 2.2759856630824373
      },
      {
        "__type__": "cc.Vec2",
        "x": 23.458781362007166,
        "y": 3.7813620071684575
      },
      {
        "__type__": "cc.Vec2",
        "x": 9.838709677419352,
        "y": 3.7813620071684575
      },
      {
        "__type__": "cc.Vec2",
        "x": 9.838709677419352,
        "y": 5.250896057347667
      },
      {
        "__type__": "cc.Vec2",
        "x": 11.344086021505376,
        "y": 5.250896057347667
      },
      {
        "__type__": "cc.Vec2",
        "x": 11.344086021505376,
        "y": 8.333333333333329
      },
      {
        "__type__": "cc.Vec2",
        "x": 9.838709677419352,
        "y": 8.333333333333329
      },
      {
        "__type__": "cc.Vec2",
        "x": 9.838709677419352,
        "y": 9.838709677419352
      },
      {
        "__type__": "cc.Vec2",
        "x": 8.333333333333329,
        "y": 9.838709677419352
      },
      {
        "__type__": "cc.Vec2",
        "x": 8.333333333333329,
        "y": 12.885304659498203
      },
      {
        "__type__": "cc.Vec2",
        "x": 6.827956989247312,
        "y": 12.885304659498203
      },
      {
        "__type__": "cc.Vec2",
        "x": 6.827956989247312,
        "y": 14.390681003584227
      },
      {
        "__type__": "cc.Vec2",
        "x": 5.286738351254478,
        "y": 14.390681003584227
      },
      {
        "__type__": "cc.Vec2",
        "x": 5.286738351254478,
        "y": 17.401433691756267
      },
      {
        "__type__": "cc.Vec2",
        "x": 3.7813620071684575,
        "y": 17.401433691756267
      },
      {
        "__type__": "cc.Vec2",
        "x": 3.7813620071684575,
        "y": 18.9426523297491
      },
      {
        "__type__": "cc.Vec2",
        "x": 2.2759856630824373,
        "y": 18.9426523297491
      },
      {
        "__type__": "cc.Vec2",
        "x": 2.2759856630824373,
        "y": 21.953405017921142
      },
      {
        "__type__": "cc.Vec2",
        "x": 0.7706093189964136,
        "y": 21.953405017921142
      },
      {
        "__type__": "cc.Vec2",
        "x": 0.7706093189964136,
        "y": 23.458781362007166
      },
      {
        "__type__": "cc.Vec2",
        "x": -0.7706093189964172,
        "y": 23.458781362007166
      },
      {
        "__type__": "cc.Vec2",
        "x": -0.7706093189964172,
        "y": 25
      }
    ],
    "_id": ""
  },
  {
    "__type__": "cc.PrefabInfo",
    "root": {
      "__id__": 1
    },
    "asset": {
      "__id__": 0
    },
    "fileId": "",
    "sync": false
  }
]